madsci/node_module/__init__.py
madsci/node_module/abstract_node_module.py
madsci/node_module/helpers.py
madsci/node_module/rest_node_module.py
madsci/node_module/type_analyzer.py
madsci_node_module-0.6.1.dist-info/METADATA
madsci_node_module-0.6.1.dist-info/WHEEL
madsci_node_module-0.6.1.dist-info/entry_points.txt
madsci_node_module-0.6.1.dist-info/RECORD
