Metadata-Version: 2.1
Name: madsci.node_module
Version: 0.6.1
Summary: The Modular Autonomous Discovery for Science (MADSci) Node Module Helper Classes.
Author-Email: Tobias Ginsburg <tginsburg@anl.gov>, "Ryan D. Lewis" <ryan.lewis@anl.gov>, Casey Stone <cstone@anl.gov>, Doga Ozgulbas <dozgulbas@anl.gov>
License: MIT
Project-URL: Homepage, https://github.com/AD-SDL/MADSci
Requires-Python: >=3.9.1
Requires-Dist: madsci.common
Requires-Dist: madsci.client
Requires-Dist: regex
